lumos/__init__.py
lumos/calculator.py
lumos/constants.py
lumos/conversions.py
lumos/functions.py
lumos/geometry.py
lumos/plot.py
lumos/brdf/__init__.py
lumos/brdf/library.py
lumos/brdf/tools.py
lumos/constellation/__init__.py
lumos/constellation/library.py
lumos/constellation/tools.py
lumos_sat-1.0.9.dist-info/LICENSE
lumos_sat-1.0.9.dist-info/METADATA
lumos_sat-1.0.9.dist-info/WHEEL
lumos_sat-1.0.9.dist-info/top_level.txt
lumos_sat-1.0.9.dist-info/RECORD
