Metadata-Version: 2.1
Name: lumos-sat
Version: 1.0.9
Summary: Satellite Brightness Calculation Tools
Author-email: Forrest Fankhauser <fafankhauser@ucdavis.edu>
Requires-Python: >=3.10
License-File: LICENSE
Requires-Dist: astropy (~=5.2.2)
Requires-Dist: matplotlib (~=3.7.1)
Requires-Dist: numpy (~=1.24.3)
Requires-Dist: opencv-python (~=4.7.0.72)
Requires-Dist: requests (~=2.30.0)
Requires-Dist: scipy (~=1.10.1)
Requires-Dist: setuptools (~=65.6.0)
Requires-Dist: sgp4 (~=2.22)
